min_lag/__init__.py
min_lag/data.py
min_lag/fields.py
min_lag/models.py
min_lag/terms.py
min_lag/unicode_util.py
min_lag/version.py
min_lag/output/LaTeX.py
min_lag/output/__init__.py
min_lag/output/plain.py
min_lag/output/SARAH/__init__.py
min_lag/output/SARAH/data/SPheno.m
min_lag/output/SARAH/data/model.m
min_lag/output/SARAH/data/parameters.m
min_lag/output/SARAH/data/particles.m
minimal_lagrangians-1.1.2.data/scripts/minimal-lagrangians
minimal_lagrangians-1.1.2.data/scripts/minimal-lagrangians.py
minimal_lagrangians-1.1.2.dist-info/LICENSE
minimal_lagrangians-1.1.2.dist-info/METADATA
minimal_lagrangians-1.1.2.dist-info/WHEEL
minimal_lagrangians-1.1.2.dist-info/top_level.txt
minimal_lagrangians-1.1.2.dist-info/RECORD
