Metadata-Version: 2.1
Name: minimal-lagrangians
Version: 1.1.2
Summary: A Python program to generate the Lagrangians for dark matter models
Home-page: https://gitlab.com/Socob/minimal-lagrangians
Author: Simon May
Author-email: simon.may@mpa-garching.mpg.de
License: GNU GPLv3
Keywords: particle physics,beyond the standard model,dark matter
Platform: OS Independent
Classifier: Programming Language :: Python :: 3
Classifier: Programming Language :: Python :: 3 :: Only
Classifier: License :: OSI Approved :: GNU General Public License v3 (GPLv3)
Classifier: Operating System :: OS Independent
Classifier: Topic :: Scientific/Engineering :: Physics
Classifier: Intended Audience :: Science/Research
Classifier: Natural Language :: English
Requires-Python: >=3.4
